{"name":"Search for a automation course","id":"academy-choucair;search-for-a-automation-course","testSteps":[{"number":1,"description":"Given than Rose want to learn automation at the Academy Choucair\r\n| strUser | strPassword |\r\n| 28869621 | Choucair2020* |","duration":42253,"startTime":"2021-04-11T14:38:51.491-05:00[America/Bogota]","screenshots":[{"screenshot":"b5219e7108f7c29245306999072dcd7fe3c0f1502e729a631c0b4a5c9c27c95d.png","timeStamp":1618169973744}],"result":"SUCCESS","precondition":false,"level":0,"lineNumber":0,"children":[{"number":2,"description":"Rose open up","duration":23944,"startTime":"2021-04-11T14:38:54.126-05:00[America/Bogota]","screenshots":[{"screenshot":"c8cfb48648e58f45a3df1ecd32cc565d7b042361dea5773a2dd4d3f5b60ce9c7.png","timeStamp":1618169958070}],"result":"SUCCESS","precondition":false,"level":1,"lineNumber":0,"children":[{"number":3,"description":"Rose opens the Choucair academy page","duration":22389,"startTime":"2021-04-11T14:38:54.254-05:00[America/Bogota]","screenshots":[{"screenshot":"c8cfb48648e58f45a3df1ecd32cc565d7b042361dea5773a2dd4d3f5b60ce9c7.png","timeStamp":1618169956640}],"result":"SUCCESS","precondition":false,"level":2,"lineNumber":0}]},{"number":4,"description":"Rose login","duration":14690,"startTime":"2021-04-11T14:39:18.076-05:00[America/Bogota]","screenshots":[{"screenshot":"a5898c47ba11df37aef7a8a504520e8d7dabe3a59d18b3ea3cbef97557bc311d.png","timeStamp":1618169972765}],"result":"SUCCESS","precondition":false,"level":1,"lineNumber":0,"children":[{"number":5,"description":"Rose clicks on  button that shows us the form to login","duration":1840,"startTime":"2021-04-11T14:39:18.291-05:00[America/Bogota]","screenshots":[{"screenshot":"e05eb8a918df337bc6b423dea234636eec70a07075f274bc9b2cf74f0dbd3266.png","timeStamp":1618169960130}],"result":"SUCCESS","precondition":false,"level":2,"lineNumber":0},{"number":6,"description":"Rose enters \u002728869621\u0027 into  button that shows us the form to login","duration":2583,"startTime":"2021-04-11T14:39:20.136-05:00[America/Bogota]","screenshots":[{"screenshot":"be7659c60c4c6228b16f0d2a80003e1579d379aaab2fee3b90934e7b4e2baa87.png","timeStamp":1618169962719}],"result":"SUCCESS","precondition":false,"level":2,"lineNumber":0},{"number":7,"description":"Rose enters \u0027Choucair2020*\u0027 into  button that shows us the form to login","duration":2230,"startTime":"2021-04-11T14:39:22.725-05:00[America/Bogota]","screenshots":[{"screenshot":"e995ed1f096df40594b53a749b6448b2388b5bd9a8b65f10ac7e80b4996095a7.png","timeStamp":1618169964955}],"result":"SUCCESS","precondition":false,"level":2,"lineNumber":0},{"number":8,"description":"Rose clicks on  button that shows us the form to login","duration":6914,"startTime":"2021-04-11T14:39:24.964-05:00[America/Bogota]","screenshots":[{"screenshot":"a5898c47ba11df37aef7a8a504520e8d7dabe3a59d18b3ea3cbef97557bc311d.png","timeStamp":1618169971878}],"result":"SUCCESS","precondition":false,"level":2,"lineNumber":0}]}]},{"number":9,"description":"When she search for the course on the choucair Academy platform\r\n| strCourse |\r\n| Metodologia Bancolombia |","duration":16008,"startTime":"2021-04-11T14:39:33.754-05:00[America/Bogota]","exception":{"errorType":"net.thucydides.core.webdriver.exceptions.ElementShouldBeEnabledException","message":"Expected enabled element was not enabled","stackTrace":[{"declaringClass":"co.com.choucair.certificacion.academy.tasks.Search","methodName":"performAs","fileName":"Search.java","lineNumber":24},{"declaringClass":"co.com.choucair.certificacion.academy.stepdefinitions.ChoucairAcademyStepDefinitions","methodName":"sheSearchForTheCourseRecursosAutomatizacionBancolombiaOnTheChoucairAcademyPlatform","fileName":"ChoucairAcademyStepDefinitions.java","lineNumber":32},{"declaringClass":"cucumber.runner.Runner","methodName":"runPickle","fileName":"Runner.java","lineNumber":80}],"rootCause":{"errorType":"org.openqa.selenium.TimeoutException","message":"Expected condition failed: waiting for By.id: coursesearchbox to be enabled (tried for 5 second(s) with 100 milliseconds interval)","stackTrace":[{"declaringClass":"co.com.choucair.certificacion.academy.tasks.Search","methodName":"performAs","fileName":"Search.java","lineNumber":24},{"declaringClass":"co.com.choucair.certificacion.academy.stepdefinitions.ChoucairAcademyStepDefinitions","methodName":"sheSearchForTheCourseRecursosAutomatizacionBancolombiaOnTheChoucairAcademyPlatform","fileName":"ChoucairAcademyStepDefinitions.java","lineNumber":32},{"declaringClass":"cucumber.runner.Runner","methodName":"runPickle","fileName":"Runner.java","lineNumber":80}],"rootCause":{"errorType":"org.openqa.selenium.NoSuchElementException","message":"no such element: Unable to locate element: {\"method\":\"css selector\",\"selector\":\"#coursesearchbox\"}\n  (Session info: chrome\u003d89.0.4389.114)\nFor documentation on this error, please visit: https://www.seleniumhq.org/exceptions/no_such_element.html\nBuild info: version: \u00273.141.59\u0027, revision: \u0027e82be7d358\u0027, time: \u00272018-11-14T08:17:03\u0027\nSystem info: host: \u0027DESKTOP-EBF6U6U\u0027, ip: \u0027192.168.56.1\u0027, os.name: \u0027Windows 10\u0027, os.arch: \u0027amd64\u0027, os.version: \u002710.0\u0027, java.version: \u00271.8.0_281\u0027\nDriver info: org.openqa.selenium.chrome.ChromeDriver\nCapabilities {acceptInsecureCerts: false, browserName: chrome, browserVersion: 89.0.4389.114, chrome: {chromedriverVersion: 89.0.4389.23 (61b08ee2c5002..., userDataDir: C:\\Users\\Personal\\AppData\\L...}, goog:chromeOptions: {debuggerAddress: localhost:52422}, javascriptEnabled: true, networkConnectionEnabled: false, pageLoadStrategy: normal, platform: WINDOWS, platformName: WINDOWS, proxy: Proxy(), setWindowRect: true, strictFileInteractability: false, timeouts: {implicit: 0, pageLoad: 300000, script: 30000}, unhandledPromptBehavior: dismiss and notify, webauthn:extension:largeBlob: true, webauthn:virtualAuthenticators: true}\nSession ID: 03d6f6fca9b04af664ae387f5fa0042f\n*** Element info: {Using\u003did, value\u003dcoursesearchbox}","stackTrace":[{"declaringClass":"co.com.choucair.certificacion.academy.tasks.Search","methodName":"performAs","fileName":"Search.java","lineNumber":24},{"declaringClass":"co.com.choucair.certificacion.academy.stepdefinitions.ChoucairAcademyStepDefinitions","methodName":"sheSearchForTheCourseRecursosAutomatizacionBancolombiaOnTheChoucairAcademyPlatform","fileName":"ChoucairAcademyStepDefinitions.java","lineNumber":32},{"declaringClass":"cucumber.runner.Runner","methodName":"runPickle","fileName":"Runner.java","lineNumber":80}]}}},"result":"FAILURE","precondition":false,"level":0,"lineNumber":0,"children":[{"number":10,"description":"Rose search","duration":15823,"startTime":"2021-04-11T14:39:33.798-05:00[America/Bogota]","exception":{"errorType":"net.thucydides.core.webdriver.exceptions.ElementShouldBeEnabledException","message":"Expected enabled element was not enabled","stackTrace":[{"declaringClass":"co.com.choucair.certificacion.academy.tasks.Search","methodName":"performAs","fileName":"Search.java","lineNumber":24},{"declaringClass":"co.com.choucair.certificacion.academy.stepdefinitions.ChoucairAcademyStepDefinitions","methodName":"sheSearchForTheCourseRecursosAutomatizacionBancolombiaOnTheChoucairAcademyPlatform","fileName":"ChoucairAcademyStepDefinitions.java","lineNumber":32},{"declaringClass":"cucumber.runner.Runner","methodName":"runPickle","fileName":"Runner.java","lineNumber":80}],"rootCause":{"errorType":"org.openqa.selenium.TimeoutException","message":"Expected condition failed: waiting for By.id: coursesearchbox to be enabled (tried for 5 second(s) with 100 milliseconds interval)","stackTrace":[{"declaringClass":"co.com.choucair.certificacion.academy.tasks.Search","methodName":"performAs","fileName":"Search.java","lineNumber":24},{"declaringClass":"co.com.choucair.certificacion.academy.stepdefinitions.ChoucairAcademyStepDefinitions","methodName":"sheSearchForTheCourseRecursosAutomatizacionBancolombiaOnTheChoucairAcademyPlatform","fileName":"ChoucairAcademyStepDefinitions.java","lineNumber":32},{"declaringClass":"cucumber.runner.Runner","methodName":"runPickle","fileName":"Runner.java","lineNumber":80}],"rootCause":{"errorType":"org.openqa.selenium.NoSuchElementException","message":"no such element: Unable to locate element: {\"method\":\"css selector\",\"selector\":\"#coursesearchbox\"}\n  (Session info: chrome\u003d89.0.4389.114)\nFor documentation on this error, please visit: https://www.seleniumhq.org/exceptions/no_such_element.html\nBuild info: version: \u00273.141.59\u0027, revision: \u0027e82be7d358\u0027, time: \u00272018-11-14T08:17:03\u0027\nSystem info: host: \u0027DESKTOP-EBF6U6U\u0027, ip: \u0027192.168.56.1\u0027, os.name: \u0027Windows 10\u0027, os.arch: \u0027amd64\u0027, os.version: \u002710.0\u0027, java.version: \u00271.8.0_281\u0027\nDriver info: org.openqa.selenium.chrome.ChromeDriver\nCapabilities {acceptInsecureCerts: false, browserName: chrome, browserVersion: 89.0.4389.114, chrome: {chromedriverVersion: 89.0.4389.23 (61b08ee2c5002..., userDataDir: C:\\Users\\Personal\\AppData\\L...}, goog:chromeOptions: {debuggerAddress: localhost:52422}, javascriptEnabled: true, networkConnectionEnabled: false, pageLoadStrategy: normal, platform: WINDOWS, platformName: WINDOWS, proxy: Proxy(), setWindowRect: true, strictFileInteractability: false, timeouts: {implicit: 0, pageLoad: 300000, script: 30000}, unhandledPromptBehavior: dismiss and notify, webauthn:extension:largeBlob: true, webauthn:virtualAuthenticators: true}\nSession ID: 03d6f6fca9b04af664ae387f5fa0042f\n*** Element info: {Using\u003did, value\u003dcoursesearchbox}","stackTrace":[{"declaringClass":"co.com.choucair.certificacion.academy.tasks.Search","methodName":"performAs","fileName":"Search.java","lineNumber":24},{"declaringClass":"co.com.choucair.certificacion.academy.stepdefinitions.ChoucairAcademyStepDefinitions","methodName":"sheSearchForTheCourseRecursosAutomatizacionBancolombiaOnTheChoucairAcademyPlatform","fileName":"ChoucairAcademyStepDefinitions.java","lineNumber":32},{"declaringClass":"cucumber.runner.Runner","methodName":"runPickle","fileName":"Runner.java","lineNumber":80}]}}},"result":"FAILURE","precondition":false,"level":1,"lineNumber":0,"children":[{"number":11,"description":"Rose clicks on selecciona la universidad choucair","duration":4164,"startTime":"2021-04-11T14:39:34.005-05:00[America/Bogota]","screenshots":[{"screenshot":"cf6787f337a3864315b1ab5d30ba4b3506748fbe13f8f6fe1fa71ebfe970f675.png","timeStamp":1618169978169}],"result":"SUCCESS","precondition":false,"level":2,"lineNumber":0},{"number":12,"description":"Rose enters \u0027Metodologia Bancolombia\u0027 into busca el curso","duration":11330,"startTime":"2021-04-11T14:39:38.173-05:00[America/Bogota]","screenshots":[{"screenshot":"cf6787f337a3864315b1ab5d30ba4b3506748fbe13f8f6fe1fa71ebfe970f675.png","htmlSource":"pagesource8228850394176786747.html.txt","timeStamp":1618169989467}],"exception":{"errorType":"net.thucydides.core.webdriver.exceptions.ElementShouldBeEnabledException","message":"Expected enabled element was not enabled","stackTrace":[{"declaringClass":"co.com.choucair.certificacion.academy.tasks.Search","methodName":"performAs","fileName":"Search.java","lineNumber":24},{"declaringClass":"co.com.choucair.certificacion.academy.stepdefinitions.ChoucairAcademyStepDefinitions","methodName":"sheSearchForTheCourseRecursosAutomatizacionBancolombiaOnTheChoucairAcademyPlatform","fileName":"ChoucairAcademyStepDefinitions.java","lineNumber":32},{"declaringClass":"cucumber.runner.Runner","methodName":"runPickle","fileName":"Runner.java","lineNumber":80}],"rootCause":{"errorType":"org.openqa.selenium.TimeoutException","message":"Expected condition failed: waiting for By.id: coursesearchbox to be enabled (tried for 5 second(s) with 100 milliseconds interval)","stackTrace":[{"declaringClass":"co.com.choucair.certificacion.academy.tasks.Search","methodName":"performAs","fileName":"Search.java","lineNumber":24},{"declaringClass":"co.com.choucair.certificacion.academy.stepdefinitions.ChoucairAcademyStepDefinitions","methodName":"sheSearchForTheCourseRecursosAutomatizacionBancolombiaOnTheChoucairAcademyPlatform","fileName":"ChoucairAcademyStepDefinitions.java","lineNumber":32},{"declaringClass":"cucumber.runner.Runner","methodName":"runPickle","fileName":"Runner.java","lineNumber":80}],"rootCause":{"errorType":"org.openqa.selenium.NoSuchElementException","message":"no such element: Unable to locate element: {\"method\":\"css selector\",\"selector\":\"#coursesearchbox\"}\n  (Session info: chrome\u003d89.0.4389.114)\nFor documentation on this error, please visit: https://www.seleniumhq.org/exceptions/no_such_element.html\nBuild info: version: \u00273.141.59\u0027, revision: \u0027e82be7d358\u0027, time: \u00272018-11-14T08:17:03\u0027\nSystem info: host: \u0027DESKTOP-EBF6U6U\u0027, ip: \u0027192.168.56.1\u0027, os.name: \u0027Windows 10\u0027, os.arch: \u0027amd64\u0027, os.version: \u002710.0\u0027, java.version: \u00271.8.0_281\u0027\nDriver info: org.openqa.selenium.chrome.ChromeDriver\nCapabilities {acceptInsecureCerts: false, browserName: chrome, browserVersion: 89.0.4389.114, chrome: {chromedriverVersion: 89.0.4389.23 (61b08ee2c5002..., userDataDir: C:\\Users\\Personal\\AppData\\L...}, goog:chromeOptions: {debuggerAddress: localhost:52422}, javascriptEnabled: true, networkConnectionEnabled: false, pageLoadStrategy: normal, platform: WINDOWS, platformName: WINDOWS, proxy: Proxy(), setWindowRect: true, strictFileInteractability: false, timeouts: {implicit: 0, pageLoad: 300000, script: 30000}, unhandledPromptBehavior: dismiss and notify, webauthn:extension:largeBlob: true, webauthn:virtualAuthenticators: true}\nSession ID: 03d6f6fca9b04af664ae387f5fa0042f\n*** Element info: {Using\u003did, value\u003dcoursesearchbox}","stackTrace":[{"declaringClass":"co.com.choucair.certificacion.academy.tasks.Search","methodName":"performAs","fileName":"Search.java","lineNumber":24},{"declaringClass":"co.com.choucair.certificacion.academy.stepdefinitions.ChoucairAcademyStepDefinitions","methodName":"sheSearchForTheCourseRecursosAutomatizacionBancolombiaOnTheChoucairAcademyPlatform","fileName":"ChoucairAcademyStepDefinitions.java","lineNumber":32},{"declaringClass":"cucumber.runner.Runner","methodName":"runPickle","fileName":"Runner.java","lineNumber":80}]}}},"result":"FAILURE","precondition":false,"level":2,"lineNumber":0}]}]},{"number":13,"description":"Then she finds the course called\r\n| strCourse |\r\n| Metodologia Bancolombia |","duration":92,"startTime":"2021-04-11T14:39:49.945-05:00[America/Bogota]","result":"SKIPPED","precondition":false,"level":0,"lineNumber":0}],"userStory":{"id":"academy-choucair","storyName":"Academy Choucair","path":"src/test/resources/features/academyChoucair.feature","narrative":"  As an user, I want to learn how to automate in screamplay at the Choucair Academy with the automation course","type":"feature"},"featureTag":{"name":"Features/Academy Choucair","type":"feature","displayName":"Features/Academy Choucair"},"title":"Search for a automation course","tags":[{"name":"scenario1","type":"tag","displayName":"scenario1"},{"name":"Academy Choucair","type":"feature","displayName":"Academy Choucair"},{"name":"stories","type":"tag","displayName":"stories"}],"startTime":"2021-04-11T14:38:50.820-05:00[America/Bogota]","duration":59314,"testFailureCause":{"errorType":"net.thucydides.core.webdriver.exceptions.ElementShouldBeEnabledException","message":"Expected enabled element was not enabled","stackTrace":[{"declaringClass":"co.com.choucair.certificacion.academy.tasks.Search","methodName":"performAs","fileName":"Search.java","lineNumber":24},{"declaringClass":"co.com.choucair.certificacion.academy.stepdefinitions.ChoucairAcademyStepDefinitions","methodName":"sheSearchForTheCourseRecursosAutomatizacionBancolombiaOnTheChoucairAcademyPlatform","fileName":"ChoucairAcademyStepDefinitions.java","lineNumber":32},{"declaringClass":"cucumber.runner.Runner","methodName":"runPickle","fileName":"Runner.java","lineNumber":80}],"rootCause":{"errorType":"org.openqa.selenium.TimeoutException","message":"Expected condition failed: waiting for By.id: coursesearchbox to be enabled (tried for 5 second(s) with 100 milliseconds interval)","stackTrace":[{"declaringClass":"co.com.choucair.certificacion.academy.tasks.Search","methodName":"performAs","fileName":"Search.java","lineNumber":24},{"declaringClass":"co.com.choucair.certificacion.academy.stepdefinitions.ChoucairAcademyStepDefinitions","methodName":"sheSearchForTheCourseRecursosAutomatizacionBancolombiaOnTheChoucairAcademyPlatform","fileName":"ChoucairAcademyStepDefinitions.java","lineNumber":32},{"declaringClass":"cucumber.runner.Runner","methodName":"runPickle","fileName":"Runner.java","lineNumber":80}],"rootCause":{"errorType":"org.openqa.selenium.NoSuchElementException","message":"no such element: Unable to locate element: {\"method\":\"css selector\",\"selector\":\"#coursesearchbox\"}\n  (Session info: chrome\u003d89.0.4389.114)\nFor documentation on this error, please visit: https://www.seleniumhq.org/exceptions/no_such_element.html\nBuild info: version: \u00273.141.59\u0027, revision: \u0027e82be7d358\u0027, time: \u00272018-11-14T08:17:03\u0027\nSystem info: host: \u0027DESKTOP-EBF6U6U\u0027, ip: \u0027192.168.56.1\u0027, os.name: \u0027Windows 10\u0027, os.arch: \u0027amd64\u0027, os.version: \u002710.0\u0027, java.version: \u00271.8.0_281\u0027\nDriver info: org.openqa.selenium.chrome.ChromeDriver\nCapabilities {acceptInsecureCerts: false, browserName: chrome, browserVersion: 89.0.4389.114, chrome: {chromedriverVersion: 89.0.4389.23 (61b08ee2c5002..., userDataDir: C:\\Users\\Personal\\AppData\\L...}, goog:chromeOptions: {debuggerAddress: localhost:52422}, javascriptEnabled: true, networkConnectionEnabled: false, pageLoadStrategy: normal, platform: WINDOWS, platformName: WINDOWS, proxy: Proxy(), setWindowRect: true, strictFileInteractability: false, timeouts: {implicit: 0, pageLoad: 300000, script: 30000}, unhandledPromptBehavior: dismiss and notify, webauthn:extension:largeBlob: true, webauthn:virtualAuthenticators: true}\nSession ID: 03d6f6fca9b04af664ae387f5fa0042f\n*** Element info: {Using\u003did, value\u003dcoursesearchbox}","stackTrace":[{"declaringClass":"co.com.choucair.certificacion.academy.tasks.Search","methodName":"performAs","fileName":"Search.java","lineNumber":24},{"declaringClass":"co.com.choucair.certificacion.academy.stepdefinitions.ChoucairAcademyStepDefinitions","methodName":"sheSearchForTheCourseRecursosAutomatizacionBancolombiaOnTheChoucairAcademyPlatform","fileName":"ChoucairAcademyStepDefinitions.java","lineNumber":32},{"declaringClass":"cucumber.runner.Runner","methodName":"runPickle","fileName":"Runner.java","lineNumber":80}]}}},"testFailureClassname":"net.thucydides.core.webdriver.exceptions.ElementShouldBeEnabledException","testFailureMessage":"Expected enabled element was not enabled","testFailureSummary":"FAILURE;net.thucydides.core.webdriver.exceptions.ElementShouldBeEnabledException;Expected enabled element was not enabled;Search.java","projectKey":"","annotatedResult":"FAILURE","sessionId":"03d6f6fca9b04af664ae387f5fa0042f","driver":"chrome:rose","isManualTestingUpToDate":false,"manual":false,"testSource":"Cucumber","actors":[{"name":"Rose","can":["browse the web"]}],"result":"FAILURE"}